circuitq/__init__.py
circuitq/core.py
circuitq/functions_file.py
circuitq-1.2.1.dist-info/LICENSE
circuitq-1.2.1.dist-info/METADATA
circuitq-1.2.1.dist-info/WHEEL
circuitq-1.2.1.dist-info/top_level.txt
circuitq-1.2.1.dist-info/RECORD
