Metadata-Version: 2.1
Name: circuitq
Version: 1.2.1
Summary: Automated design of superconducting qubits
Home-page: https://github.com/PhilippAumann/circuitq
Author: CircuitQ Team
Author-email: philipp.aumann@uibk.ac.at
License: MIT
Platform: UNKNOWN
License-File: LICENSE
Requires-Dist: numpy
Requires-Dist: networkx
Requires-Dist: sympy
Requires-Dist: scipy
